royalspells/__init__.py
royalspells/main.py
royalspells-4.0.3.dist-info/METADATA
royalspells-4.0.3.dist-info/WHEEL
royalspells-4.0.3.dist-info/licenses/LICENSE.txt
royalspells-4.0.3.dist-info/RECORD
