Metadata-Version: 2.4
Name: royalspells
Version: 4.0.3
Summary: Genera proceduralmente magie con statistiche insignificanti
License-Expression: EUPL-1.2
License-File: LICENSE.txt
Keywords: ryg,silly
Author: Stefano Pigozzi
Author-email: me@steffo.eu
Maintainer: Stefano Pigozzi
Maintainer-email: me@steffo.eu
Requires-Python: >=3.6,<4.0
Classifier: Programming Language :: Python :: 3
Classifier: Programming Language :: Python :: 3.6
Classifier: Programming Language :: Python :: 3.7
Classifier: Programming Language :: Python :: 3.8
Classifier: Programming Language :: Python :: 3.9
Classifier: Programming Language :: Python :: 3.10
Classifier: Programming Language :: Python :: 3.11
Classifier: Programming Language :: Python :: 3.12
Classifier: Programming Language :: Python :: 3.13
Classifier: Development Status :: 7 - Inactive
Classifier: Intended Audience :: Developers
Classifier: License :: OSI Approved :: European Union Public Licence 1.2 (EUPL 1.2)
Classifier: Natural Language :: Italian
Classifier: Operating System :: OS Independent
Project-URL: Source, https://forge.steffo.eu/steffo/royalspells
